slurmbot/__init__.py
slurmbot/err
slurmbot/out
slurmbot/sa
slurmbot/sc
slurmbot/scripts.py
slurmbot/slurmbot.py
slurmbot/sq
slurmbot-0.2.3.dist-info/METADATA
slurmbot-0.2.3.dist-info/WHEEL
slurmbot-0.2.3.dist-info/RECORD
