Metadata-Version: 2.1
Name: slurmbot
Version: 0.2.3
Summary: Simple tool to wrap and execute sbatch commands from `python` scripts or `Jupyter Notebook` cells with `conda` envs and config files. Secure and reproducible
License: MIT
Author: Dmitry Solovey
Author-email: dsolovey@ist.ac.at
Requires-Python: >=3.9,<4.0
Classifier: License :: OSI Approved :: MIT License
Classifier: Programming Language :: Python :: 3
Classifier: Programming Language :: Python :: 3.9
Classifier: Programming Language :: Python :: 3.10
Classifier: Programming Language :: Python :: 3.11
Classifier: Programming Language :: Python :: 3.12
